{"type":"health-data","date":"2026-05-30","units":"metric","activity":{"steps":21000,"walkingRunningDistanceKm":15.49,"walkingRunningDistance":15490,"activeCalories":1180,"exerciseMinutes":106,"vo2Max":42.9,"basalEnergyBurned":1621,"standHours":14,"flightsClimbed":12},"heart":{"averageHeartRate":74.9,"heartRateMin":56,"heartRateMax":150,"heartRateSamples":[{"timestamp":"2026-05-30T00:00:00","value":58},{"timestamp":"2026-05-30T00:15:00","value":64},{"timestamp":"2026-05-30T00:30:00","value":58},{"timestamp":"2026-05-30T00:45:00","value":63},{"timestamp":"2026-05-30T01:00:00","value":62},{"timestamp":"2026-05-30T01:15:00","value":58},{"timestamp":"2026-05-30T01:30:00","value":60},{"timestamp":"2026-05-30T01:45:00","value":65},{"timestamp":"2026-05-30T02:00:00","value":59},{"timestamp":"2026-05-30T02:15:00","value":59},{"timestamp":"2026-05-30T02:30:00","value":62},{"timestamp":"2026-05-30T02:45:00","value":62},{"timestamp":"2026-05-30T03:00:00","value":64},{"timestamp":"2026-05-30T03:15:00","value":62},{"timestamp":"2026-05-30T03:30:00","value":56},{"timestamp":"2026-05-30T03:45:00","value":60},{"timestamp":"2026-05-30T04:00:00","value":59},{"timestamp":"2026-05-30T04:15:00","value":59},{"timestamp":"2026-05-30T04:30:00","value":58},{"timestamp":"2026-05-30T04:45:00","value":61},{"timestamp":"2026-05-30T05:00:00","value":56},{"timestamp":"2026-05-30T05:15:00","value":62},{"timestamp":"2026-05-30T05:30:00","value":64},{"timestamp":"2026-05-30T05:45:00","value":60},{"timestamp":"2026-05-30T06:00:00","value":63},{"timestamp":"2026-05-30T06:15:00","value":57},{"timestamp":"2026-05-30T06:30:00","value":59},{"timestamp":"2026-05-30T06:45:00","value":74},{"timestamp":"2026-05-30T07:00:00","value":66},{"timestamp":"2026-05-30T07:15:00","value":75},{"timestamp":"2026-05-30T07:30:00","value":74},{"timestamp":"2026-05-30T07:45:00","value":76},{"timestamp":"2026-05-30T08:00:00","value":66},{"timestamp":"2026-05-30T08:15:00","value":83},{"timestamp":"2026-05-30T08:30:00","value":95},{"timestamp":"2026-05-30T08:45:00","value":116},{"timestamp":"2026-05-30T09:00:00","value":147},{"timestamp":"2026-05-30T09:15:00","value":150},{"timestamp":"2026-05-30T09:30:00","value":139},{"timestamp":"2026-05-30T09:45:00","value":125},{"timestamp":"2026-05-30T10:00:00","value":107},{"timestamp":"2026-05-30T10:15:00","value":93},{"timestamp":"2026-05-30T10:30:00","value":71},{"timestamp":"2026-05-30T10:45:00","value":74},{"timestamp":"2026-05-30T11:00:00","value":75},{"timestamp":"2026-05-30T11:15:00","value":75},{"timestamp":"2026-05-30T11:30:00","value":74},{"timestamp":"2026-05-30T11:45:00","value":73},{"timestamp":"2026-05-30T12:00:00","value":82},{"timestamp":"2026-05-30T12:15:00","value":73},{"timestamp":"2026-05-30T12:30:00","value":81},{"timestamp":"2026-05-30T12:45:00","value":73},{"timestamp":"2026-05-30T13:00:00","value":79},{"timestamp":"2026-05-30T13:15:00","value":83},{"timestamp":"2026-05-30T13:30:00","value":76},{"timestamp":"2026-05-30T13:45:00","value":78},{"timestamp":"2026-05-30T14:00:00","value":76},{"timestamp":"2026-05-30T14:15:00","value":77},{"timestamp":"2026-05-30T14:30:00","value":75},{"timestamp":"2026-05-30T14:45:00","value":78},{"timestamp":"2026-05-30T15:00:00","value":84},{"timestamp":"2026-05-30T15:15:00","value":77},{"timestamp":"2026-05-30T15:30:00","value":83},{"timestamp":"2026-05-30T15:45:00","value":77},{"timestamp":"2026-05-30T16:00:00","value":74},{"timestamp":"2026-05-30T16:15:00","value":83},{"timestamp":"2026-05-30T16:30:00","value":83},{"timestamp":"2026-05-30T16:45:00","value":83},{"timestamp":"2026-05-30T17:00:00","value":75},{"timestamp":"2026-05-30T17:15:00","value":82},{"timestamp":"2026-05-30T17:30:00","value":81},{"timestamp":"2026-05-30T17:45:00","value":82},{"timestamp":"2026-05-30T18:00:00","value":80},{"timestamp":"2026-05-30T18:15:00","value":84},{"timestamp":"2026-05-30T18:30:00","value":75},{"timestamp":"2026-05-30T18:45:00","value":82},{"timestamp":"2026-05-30T19:00:00","value":78},{"timestamp":"2026-05-30T19:15:00","value":75},{"timestamp":"2026-05-30T19:30:00","value":69},{"timestamp":"2026-05-30T19:45:00","value":72},{"timestamp":"2026-05-30T20:00:00","value":74},{"timestamp":"2026-05-30T20:15:00","value":69},{"timestamp":"2026-05-30T20:30:00","value":70},{"timestamp":"2026-05-30T20:45:00","value":71},{"timestamp":"2026-05-30T21:00:00","value":74},{"timestamp":"2026-05-30T21:15:00","value":78},{"timestamp":"2026-05-30T21:30:00","value":78},{"timestamp":"2026-05-30T21:45:00","value":78},{"timestamp":"2026-05-30T22:00:00","value":72},{"timestamp":"2026-05-30T22:15:00","value":77},{"timestamp":"2026-05-30T22:30:00","value":70},{"timestamp":"2026-05-30T22:45:00","value":65},{"timestamp":"2026-05-30T23:00:00","value":63},{"timestamp":"2026-05-30T23:15:00","value":63},{"timestamp":"2026-05-30T23:30:00","value":60},{"timestamp":"2026-05-30T23:45:00","value":60}],"hrvSamples":[{"timestamp":"2026-05-30T02:45:00","value":47.7},{"timestamp":"2026-05-30T04:15:00","value":47.9}],"hrv":49.7,"restingHeartRate":60,"walkingHeartRateAverage":97},"vitals":{"bloodOxygenSamples":[{"timestamp":"2026-05-30T00:45:00","value":97.8,"percent":97.8},{"timestamp":"2026-05-30T02:00:00","value":97.6,"percent":97.6},{"timestamp":"2026-05-30T03:15:00","value":96.5,"percent":96.5},{"timestamp":"2026-05-30T04:30:00","value":97.5,"percent":97.5},{"timestamp":"2026-05-30T05:45:00","value":97.7,"percent":97.7},{"timestamp":"2026-05-30T07:00:00","value":97,"percent":97},{"timestamp":"2026-05-30T15:00:00","value":97.1,"percent":97.1},{"timestamp":"2026-05-30T22:00:00","value":96.6,"percent":96.6}],"respiratoryRateSamples":[{"timestamp":"2026-05-30T00:45:00","value":14.2},{"timestamp":"2026-05-30T02:00:00","value":14.9},{"timestamp":"2026-05-30T03:15:00","value":14.3},{"timestamp":"2026-05-30T04:30:00","value":13.8},{"timestamp":"2026-05-30T05:45:00","value":14.5},{"timestamp":"2026-05-30T07:00:00","value":14.6},{"timestamp":"2026-05-30T15:00:00","value":14.7},{"timestamp":"2026-05-30T22:00:00","value":14.1}],"bloodOxygenPercent":97.2,"bloodOxygenAvg":97.2,"bloodOxygenMin":96.5,"bloodOxygenMax":97.8,"respiratoryRate":14.4,"respiratoryRateAvg":14.4,"respiratoryRateMin":13.8,"respiratoryRateMax":14.9},"sleep":{"sleepStages":[{"stage":"awake","startDate":"2026-05-30T23:29:00","endDate":"2026-05-30T23:40:00","durationSeconds":668},{"stage":"core","startDate":"2026-05-30T23:40:00","endDate":"2026-05-31T00:31:00","durationSeconds":3075},{"stage":"deep","startDate":"2026-05-31T00:31:00","endDate":"2026-05-31T01:28:00","durationSeconds":3375},{"stage":"core","startDate":"2026-05-31T01:28:00","endDate":"2026-05-31T02:04:00","durationSeconds":2167},{"stage":"rem","startDate":"2026-05-31T02:04:00","endDate":"2026-05-31T02:25:00","durationSeconds":1296},{"stage":"awake","startDate":"2026-05-31T02:25:00","endDate":"2026-05-31T02:28:00","durationSeconds":165},{"stage":"core","startDate":"2026-05-31T02:28:00","endDate":"2026-05-31T03:40:00","durationSeconds":4325},{"stage":"deep","startDate":"2026-05-31T03:40:00","endDate":"2026-05-31T04:11:00","durationSeconds":1879},{"stage":"core","startDate":"2026-05-31T04:11:00","endDate":"2026-05-31T04:51:00","durationSeconds":2392},{"stage":"rem","startDate":"2026-05-31T04:51:00","endDate":"2026-05-31T05:26:00","durationSeconds":2097},{"stage":"awake","startDate":"2026-05-31T05:26:00","endDate":"2026-05-31T05:28:00","durationSeconds":110},{"stage":"core","startDate":"2026-05-31T05:28:00","endDate":"2026-05-31T07:04:00","durationSeconds":5759},{"stage":"deep","startDate":"2026-05-31T07:04:00","endDate":"2026-05-31T07:21:00","durationSeconds":997},{"stage":"core","startDate":"2026-05-31T07:21:00","endDate":"2026-05-31T07:35:00","durationSeconds":860},{"stage":"awake","startDate":"2026-05-31T07:35:00","endDate":"2026-05-31T07:41:00","durationSeconds":389},{"stage":"awake","startDate":"2026-05-31T07:41:00","endDate":"2026-05-31T08:03:00","durationSeconds":1289}],"totalDuration":28222,"totalDurationFormatted":"7h 50m","deepSleep":6251,"deepSleepFormatted":"1h 44m","remSleep":3393,"remSleepFormatted":"57m","coreSleep":18578,"coreSleepFormatted":"5h 10m","awakeTime":2621,"awakeTimeFormatted":"44m","bedtime":"2026-05-30T23:29:00","wakeTime":"2026-05-31T08:03:00"},"mobility":{"walkingSpeed":1.26,"walkingAsymmetryPercentage":1.4,"walkingStepLength":0.79,"walkingDoubleSupportPercentage":26.3,"stairAscentSpeed":0.53,"stairDescentSpeed":0.54},"hearing":{"headphoneAudioLevel":59.2},"workouts":[{"type":"hiking","duration":5907,"durationFormatted":"1h 38m","calories":774,"startTime":"2026-05-30T08:27:00","avgHeartRate":128,"maxHeartRate":141,"minHeartRate":85,"timeSeries":{"heartRate":[{"timestamp":"2026-05-30T08:27:00","value":85},{"timestamp":"2026-05-30T08:28:00","value":85},{"timestamp":"2026-05-30T08:29:00","value":91},{"timestamp":"2026-05-30T08:30:00","value":99},{"timestamp":"2026-05-30T08:31:00","value":104},{"timestamp":"2026-05-30T08:32:00","value":106},{"timestamp":"2026-05-30T08:33:00","value":109},{"timestamp":"2026-05-30T08:34:00","value":109},{"timestamp":"2026-05-30T08:35:00","value":114},{"timestamp":"2026-05-30T08:36:00","value":111},{"timestamp":"2026-05-30T08:37:00","value":113},{"timestamp":"2026-05-30T08:38:00","value":119},{"timestamp":"2026-05-30T08:39:00","value":116},{"timestamp":"2026-05-30T08:40:00","value":118},{"timestamp":"2026-05-30T08:41:00","value":124},{"timestamp":"2026-05-30T08:42:00","value":123},{"timestamp":"2026-05-30T08:43:00","value":131},{"timestamp":"2026-05-30T08:44:00","value":133},{"timestamp":"2026-05-30T08:45:00","value":138},{"timestamp":"2026-05-30T08:46:00","value":135},{"timestamp":"2026-05-30T08:47:00","value":140},{"timestamp":"2026-05-30T08:48:00","value":141},{"timestamp":"2026-05-30T08:49:00","value":137},{"timestamp":"2026-05-30T08:50:00","value":139},{"timestamp":"2026-05-30T08:51:00","value":138},{"timestamp":"2026-05-30T08:52:00","value":137},{"timestamp":"2026-05-30T08:53:00","value":141},{"timestamp":"2026-05-30T08:54:00","value":141},{"timestamp":"2026-05-30T08:55:00","value":140},{"timestamp":"2026-05-30T08:56:00","value":136},{"timestamp":"2026-05-30T08:57:00","value":139},{"timestamp":"2026-05-30T08:58:00","value":137},{"timestamp":"2026-05-30T08:59:00","value":133},{"timestamp":"2026-05-30T09:00:00","value":137},{"timestamp":"2026-05-30T09:01:00","value":131},{"timestamp":"2026-05-30T09:02:00","value":133},{"timestamp":"2026-05-30T09:03:00","value":135},{"timestamp":"2026-05-30T09:04:00","value":136},{"timestamp":"2026-05-30T09:05:00","value":134},{"timestamp":"2026-05-30T09:06:00","value":138},{"timestamp":"2026-05-30T09:07:00","value":141},{"timestamp":"2026-05-30T09:08:00","value":137},{"timestamp":"2026-05-30T09:09:00","value":139},{"timestamp":"2026-05-30T09:10:00","value":138},{"timestamp":"2026-05-30T09:11:00","value":138},{"timestamp":"2026-05-30T09:12:00","value":135},{"timestamp":"2026-05-30T09:13:00","value":141},{"timestamp":"2026-05-30T09:14:00","value":136},{"timestamp":"2026-05-30T09:15:00","value":137},{"timestamp":"2026-05-30T09:16:00","value":137},{"timestamp":"2026-05-30T09:17:00","value":140},{"timestamp":"2026-05-30T09:18:00","value":136},{"timestamp":"2026-05-30T09:19:00","value":135},{"timestamp":"2026-05-30T09:20:00","value":132},{"timestamp":"2026-05-30T09:21:00","value":132},{"timestamp":"2026-05-30T09:22:00","value":133},{"timestamp":"2026-05-30T09:23:00","value":135},{"timestamp":"2026-05-30T09:24:00","value":138},{"timestamp":"2026-05-30T09:25:00","value":137},{"timestamp":"2026-05-30T09:26:00","value":135},{"timestamp":"2026-05-30T09:27:00","value":140},{"timestamp":"2026-05-30T09:28:00","value":139},{"timestamp":"2026-05-30T09:29:00","value":138},{"timestamp":"2026-05-30T09:30:00","value":140},{"timestamp":"2026-05-30T09:31:00","value":140},{"timestamp":"2026-05-30T09:32:00","value":138},{"timestamp":"2026-05-30T09:33:00","value":139},{"timestamp":"2026-05-30T09:34:00","value":140},{"timestamp":"2026-05-30T09:35:00","value":139},{"timestamp":"2026-05-30T09:36:00","value":135},{"timestamp":"2026-05-30T09:37:00","value":140},{"timestamp":"2026-05-30T09:38:00","value":133},{"timestamp":"2026-05-30T09:39:00","value":132},{"timestamp":"2026-05-30T09:40:00","value":136},{"timestamp":"2026-05-30T09:41:00","value":136},{"timestamp":"2026-05-30T09:42:00","value":137},{"timestamp":"2026-05-30T09:43:00","value":135},{"timestamp":"2026-05-30T09:44:00","value":133},{"timestamp":"2026-05-30T09:45:00","value":137},{"timestamp":"2026-05-30T09:46:00","value":137},{"timestamp":"2026-05-30T09:47:00","value":139},{"timestamp":"2026-05-30T09:48:00","value":141},{"timestamp":"2026-05-30T09:49:00","value":138},{"timestamp":"2026-05-30T09:50:00","value":133},{"timestamp":"2026-05-30T09:51:00","value":136},{"timestamp":"2026-05-30T09:52:00","value":130},{"timestamp":"2026-05-30T09:53:00","value":127},{"timestamp":"2026-05-30T09:54:00","value":122},{"timestamp":"2026-05-30T09:55:00","value":118},{"timestamp":"2026-05-30T09:56:00","value":113},{"timestamp":"2026-05-30T09:57:00","value":109},{"timestamp":"2026-05-30T09:58:00","value":101},{"timestamp":"2026-05-30T09:59:00","value":101},{"timestamp":"2026-05-30T10:00:00","value":95},{"timestamp":"2026-05-30T10:01:00","value":96},{"timestamp":"2026-05-30T10:02:00","value":89},{"timestamp":"2026-05-30T10:03:00","value":89},{"timestamp":"2026-05-30T10:04:00","value":89},{"timestamp":"2026-05-30T10:05:00","value":86}]},"distance":9.26,"distanceFormatted":"9.26 km","avgPaceFormatted":"10:38/km","avgSpeedFormatted":"5.6 km/h","route":[{"timestamp":"2026-05-30T08:27:00","latitude":37.768324,"longitude":-122.472103,"altitude":46.4,"speedMps":1.37,"courseDegrees":357,"horizontalAccuracyMeters":4},{"timestamp":"2026-05-30T08:28:00","latitude":37.770135,"longitude":-122.471598,"altitude":47.6,"speedMps":1.3,"courseDegrees":5,"horizontalAccuracyMeters":4.9},{"timestamp":"2026-05-30T08:30:00","latitude":37.771521,"longitude":-122.471352,"altitude":50.3,"speedMps":1.73,"courseDegrees":11,"horizontalAccuracyMeters":3.7},{"timestamp":"2026-05-30T08:31:00","latitude":37.772288,"longitude":-122.471218,"altitude":56.6,"speedMps":1.8,"courseDegrees":14,"horizontalAccuracyMeters":4.3},{"timestamp":"2026-05-30T08:33:00","latitude":37.774754,"longitude":-122.471942,"altitude":58.5,"speedMps":1.78,"courseDegrees":24,"horizontalAccuracyMeters":4.2},{"timestamp":"2026-05-30T08:34:00","latitude":37.776263,"longitude":-122.472802,"altitude":60.8,"speedMps":1.32,"courseDegrees":31,"horizontalAccuracyMeters":8.6},{"timestamp":"2026-05-30T08:36:00","latitude":37.775725,"longitude":-122.47275,"altitude":61.4,"speedMps":1.31,"courseDegrees":29,"horizontalAccuracyMeters":7.3},{"timestamp":"2026-05-30T08:37:00","latitude":37.776849,"longitude":-122.473931,"altitude":61.4,"speedMps":1.33,"courseDegrees":36,"horizontalAccuracyMeters":4.4},{"timestamp":"2026-05-30T08:39:00","latitude":37.778406,"longitude":-122.475991,"altitude":64.1,"speedMps":1.48,"courseDegrees":47,"horizontalAccuracyMeters":7.9},{"timestamp":"2026-05-30T08:40:00","latitude":37.778511,"longitude":-122.477012,"altitude":61.3,"speedMps":1.45,"courseDegrees":51,"horizontalAccuracyMeters":6.8},{"timestamp":"2026-05-30T08:42:00","latitude":37.778901,"longitude":-122.478632,"altitude":61.6,"speedMps":1.64,"courseDegrees":58,"horizontalAccuracyMeters":5.1},{"timestamp":"2026-05-30T08:43:00","latitude":37.778982,"longitude":-122.48004,"altitude":62,"speedMps":1.63,"courseDegrees":65,"horizontalAccuracyMeters":5.1},{"timestamp":"2026-05-30T08:45:00","latitude":37.778832,"longitude":-122.481047,"altitude":59.3,"speedMps":1.38,"courseDegrees":69,"horizontalAccuracyMeters":4},{"timestamp":"2026-05-30T08:46:00","latitude":37.778509,"longitude":-122.481383,"altitude":55.1,"speedMps":1.76,"courseDegrees":70,"horizontalAccuracyMeters":7.7},{"timestamp":"2026-05-30T08:48:00","latitude":37.778726,"longitude":-122.483336,"altitude":54.1,"speedMps":1.59,"courseDegrees":81,"horizontalAccuracyMeters":8.9},{"timestamp":"2026-05-30T08:49:00","latitude":37.778572,"longitude":-122.483013,"altitude":47.4,"speedMps":1.84,"courseDegrees":79,"horizontalAccuracyMeters":8.9},{"timestamp":"2026-05-30T08:51:00","latitude":37.778806,"longitude":-122.484227,"altitude":46.1,"speedMps":1.51,"courseDegrees":87,"horizontalAccuracyMeters":6.4},{"timestamp":"2026-05-30T08:52:00","latitude":37.77908,"longitude":-122.484885,"altitude":41.5,"speedMps":1.74,"courseDegrees":90,"horizontalAccuracyMeters":8.8},{"timestamp":"2026-05-30T08:54:00","latitude":37.779258,"longitude":-122.48703,"altitude":37.1,"speedMps":1.35,"courseDegrees":102,"horizontalAccuracyMeters":5.5},{"timestamp":"2026-05-30T08:55:00","latitude":37.779745,"longitude":-122.487263,"altitude":36.9,"speedMps":1.7,"courseDegrees":103,"horizontalAccuracyMeters":8.2},{"timestamp":"2026-05-30T08:57:00","latitude":37.779617,"longitude":-122.489563,"altitude":34.1,"speedMps":1.54,"courseDegrees":114,"horizontalAccuracyMeters":4.8},{"timestamp":"2026-05-30T08:58:00","latitude":37.780227,"longitude":-122.489725,"altitude":30.5,"speedMps":1.63,"courseDegrees":113,"horizontalAccuracyMeters":5.6},{"timestamp":"2026-05-30T09:00:00","latitude":37.779864,"longitude":-122.491694,"altitude":27.3,"speedMps":1.53,"courseDegrees":122,"horizontalAccuracyMeters":8},{"timestamp":"2026-05-30T09:01:00","latitude":37.779397,"longitude":-122.493245,"altitude":27.5,"speedMps":1.76,"courseDegrees":129,"horizontalAccuracyMeters":6.5},{"timestamp":"2026-05-30T09:03:00","latitude":37.779413,"longitude":-122.493848,"altitude":26.3,"speedMps":1.64,"courseDegrees":131,"horizontalAccuracyMeters":4.8},{"timestamp":"2026-05-30T09:04:00","latitude":37.778595,"longitude":-122.495058,"altitude":28.1,"speedMps":1.77,"courseDegrees":137,"horizontalAccuracyMeters":7.6},{"timestamp":"2026-05-30T09:06:00","latitude":37.776699,"longitude":-122.496649,"altitude":28,"speedMps":1.81,"courseDegrees":147,"horizontalAccuracyMeters":4.2},{"timestamp":"2026-05-30T09:07:00","latitude":37.77522,"longitude":-122.497376,"altitude":31.2,"speedMps":1.51,"courseDegrees":153,"horizontalAccuracyMeters":7.7},{"timestamp":"2026-05-30T09:09:00","latitude":37.773817,"longitude":-122.497686,"altitude":32.8,"speedMps":1.61,"courseDegrees":159,"horizontalAccuracyMeters":5},{"timestamp":"2026-05-30T09:10:00","latitude":37.772841,"longitude":-122.497568,"altitude":33,"speedMps":1.52,"courseDegrees":163,"horizontalAccuracyMeters":7.8},{"timestamp":"2026-05-30T09:12:00","latitude":37.772562,"longitude":-122.497087,"altitude":38,"speedMps":1.51,"courseDegrees":163,"horizontalAccuracyMeters":4.7},{"timestamp":"2026-05-30T09:13:00","latitude":37.770637,"longitude":-122.496889,"altitude":40.2,"speedMps":1.32,"courseDegrees":172,"horizontalAccuracyMeters":8.7},{"timestamp":"2026-05-30T09:15:00","latitude":37.769929,"longitude":-122.496345,"altitude":42.1,"speedMps":1.73,"courseDegrees":175,"horizontalAccuracyMeters":6.9},{"timestamp":"2026-05-30T09:16:00","latitude":37.768408,"longitude":-122.495793,"altitude":45.1,"speedMps":1.5,"courseDegrees":183,"horizontalAccuracyMeters":4.9},{"timestamp":"2026-05-30T09:18:00","latitude":37.766772,"longitude":-122.495085,"altitude":50.3,"speedMps":1.83,"courseDegrees":192,"horizontalAccuracyMeters":5.3},{"timestamp":"2026-05-30T09:20:00","latitude":37.766999,"longitude":-122.49475,"altitude":51.5,"speedMps":1.33,"courseDegrees":191,"horizontalAccuracyMeters":4.4},{"timestamp":"2026-05-30T09:21:00","latitude":37.765056,"longitude":-122.493938,"altitude":55.5,"speedMps":1.31,"courseDegrees":203,"horizontalAccuracyMeters":7.8},{"timestamp":"2026-05-30T09:23:00","latitude":37.765062,"longitude":-122.4939,"altitude":58.7,"speedMps":1.62,"courseDegrees":203,"horizontalAccuracyMeters":7.7},{"timestamp":"2026-05-30T09:24:00","latitude":37.763982,"longitude":-122.493526,"altitude":59.9,"speedMps":1.62,"courseDegrees":209,"horizontalAccuracyMeters":6.9},{"timestamp":"2026-05-30T09:26:00","latitude":37.762606,"longitude":-122.492983,"altitude":60.2,"speedMps":1.45,"courseDegrees":218,"horizontalAccuracyMeters":4},{"timestamp":"2026-05-30T09:27:00","latitude":37.76141,"longitude":-122.492543,"altitude":64.5,"speedMps":1.67,"courseDegrees":224,"horizontalAccuracyMeters":4.9},{"timestamp":"2026-05-30T09:29:00","latitude":37.760381,"longitude":-122.492266,"altitude":62.9,"speedMps":1.48,"courseDegrees":229,"horizontalAccuracyMeters":7.1},{"timestamp":"2026-05-30T09:30:00","latitude":37.759282,"longitude":-122.491875,"altitude":60.7,"speedMps":1.67,"courseDegrees":234,"horizontalAccuracyMeters":4.9},{"timestamp":"2026-05-30T09:32:00","latitude":37.758014,"longitude":-122.491059,"altitude":60.5,"speedMps":1.41,"courseDegrees":240,"horizontalAccuracyMeters":5},{"timestamp":"2026-05-30T09:33:00","latitude":37.757292,"longitude":-122.490938,"altitude":60.6,"speedMps":1.71,"courseDegrees":242,"horizontalAccuracyMeters":8.2},{"timestamp":"2026-05-30T09:35:00","latitude":37.755966,"longitude":-122.489029,"altitude":58.5,"speedMps":1.83,"courseDegrees":252,"horizontalAccuracyMeters":6},{"timestamp":"2026-05-30T09:36:00","latitude":37.755612,"longitude":-122.489068,"altitude":53.6,"speedMps":1.63,"courseDegrees":252,"horizontalAccuracyMeters":6.3},{"timestamp":"2026-05-30T09:38:00","latitude":37.754884,"longitude":-122.486639,"altitude":49.4,"speedMps":1.83,"courseDegrees":263,"horizontalAccuracyMeters":3.8},{"timestamp":"2026-05-30T09:39:00","latitude":37.754803,"longitude":-122.485924,"altitude":48,"speedMps":1.74,"courseDegrees":266,"horizontalAccuracyMeters":5},{"timestamp":"2026-05-30T09:41:00","latitude":37.754945,"longitude":-122.484216,"altitude":46.1,"speedMps":1.82,"courseDegrees":273,"horizontalAccuracyMeters":8.2},{"timestamp":"2026-05-30T09:42:00","latitude":37.755469,"longitude":-122.482498,"altitude":40.8,"speedMps":1.38,"courseDegrees":280,"horizontalAccuracyMeters":7.9},{"timestamp":"2026-05-30T09:44:00","latitude":37.755922,"longitude":-122.482647,"altitude":38.9,"speedMps":1.33,"courseDegrees":280,"horizontalAccuracyMeters":3.7},{"timestamp":"2026-05-30T09:45:00","latitude":37.756734,"longitude":-122.481585,"altitude":33.2,"speedMps":1.51,"courseDegrees":285,"horizontalAccuracyMeters":8.5},{"timestamp":"2026-05-30T09:47:00","latitude":37.757699,"longitude":-122.480603,"altitude":33.4,"speedMps":1.69,"courseDegrees":291,"horizontalAccuracyMeters":4.1},{"timestamp":"2026-05-30T09:48:00","latitude":37.758824,"longitude":-122.479594,"altitude":29.8,"speedMps":1.35,"courseDegrees":297,"horizontalAccuracyMeters":3.7},{"timestamp":"2026-05-30T09:50:00","latitude":37.760232,"longitude":-122.478399,"altitude":28.6,"speedMps":1.51,"courseDegrees":307,"horizontalAccuracyMeters":4.1},{"timestamp":"2026-05-30T09:51:00","latitude":37.760733,"longitude":-122.478504,"altitude":26.8,"speedMps":1.36,"courseDegrees":308,"horizontalAccuracyMeters":8.1},{"timestamp":"2026-05-30T09:53:00","latitude":37.761837,"longitude":-122.47774,"altitude":29,"speedMps":1.66,"courseDegrees":315,"horizontalAccuracyMeters":4.9},{"timestamp":"2026-05-30T09:54:00","latitude":37.762918,"longitude":-122.477004,"altitude":29,"speedMps":1.75,"courseDegrees":323,"horizontalAccuracyMeters":7.2},{"timestamp":"2026-05-30T09:56:00","latitude":37.763606,"longitude":-122.476496,"altitude":26.6,"speedMps":1.61,"courseDegrees":328,"horizontalAccuracyMeters":6.6},{"timestamp":"2026-05-30T09:57:00","latitude":37.764761,"longitude":-122.475646,"altitude":29.2,"speedMps":1.73,"courseDegrees":336,"horizontalAccuracyMeters":7.3},{"timestamp":"2026-05-30T09:59:00","latitude":37.764876,"longitude":-122.475203,"altitude":31.8,"speedMps":1.73,"courseDegrees":337,"horizontalAccuracyMeters":6.9},{"timestamp":"2026-05-30T10:00:00","latitude":37.765309,"longitude":-122.474511,"altitude":34,"speedMps":1.47,"courseDegrees":341,"horizontalAccuracyMeters":6.5},{"timestamp":"2026-05-30T10:02:00","latitude":37.767456,"longitude":-122.473414,"altitude":39.6,"speedMps":1.75,"courseDegrees":353,"horizontalAccuracyMeters":8.2},{"timestamp":"2026-05-30T10:03:00","latitude":37.766907,"longitude":-122.472866,"altitude":42,"speedMps":1.7,"courseDegrees":351,"horizontalAccuracyMeters":8.2},{"timestamp":"2026-05-30T10:05:00","latitude":37.769377,"longitude":-122.472099,"altitude":44.4,"speedMps":1.66,"courseDegrees":2,"horizontalAccuracyMeters":4.2}]}]}
