{"type":"health-data","date":"2026-03-31","units":"metric","activity":{"steps":17888,"walkingRunningDistanceKm":14.87,"walkingRunningDistance":14870,"activeCalories":1097,"exerciseMinutes":59,"vo2Max":42.5,"basalEnergyBurned":1622,"standHours":14,"flightsClimbed":14},"heart":{"averageHeartRate":74.7,"heartRateMin":57,"heartRateMax":149,"heartRateSamples":[{"timestamp":"2026-03-31T00:00:00","value":65},{"timestamp":"2026-03-31T00:15:00","value":65},{"timestamp":"2026-03-31T00:30:00","value":57},{"timestamp":"2026-03-31T00:45:00","value":61},{"timestamp":"2026-03-31T01:00:00","value":66},{"timestamp":"2026-03-31T01:15:00","value":57},{"timestamp":"2026-03-31T01:30:00","value":61},{"timestamp":"2026-03-31T01:45:00","value":65},{"timestamp":"2026-03-31T02:00:00","value":60},{"timestamp":"2026-03-31T02:15:00","value":58},{"timestamp":"2026-03-31T02:30:00","value":57},{"timestamp":"2026-03-31T02:45:00","value":66},{"timestamp":"2026-03-31T03:00:00","value":57},{"timestamp":"2026-03-31T03:15:00","value":58},{"timestamp":"2026-03-31T03:30:00","value":62},{"timestamp":"2026-03-31T03:45:00","value":65},{"timestamp":"2026-03-31T04:00:00","value":66},{"timestamp":"2026-03-31T04:15:00","value":57},{"timestamp":"2026-03-31T04:30:00","value":57},{"timestamp":"2026-03-31T04:45:00","value":61},{"timestamp":"2026-03-31T05:00:00","value":63},{"timestamp":"2026-03-31T05:15:00","value":58},{"timestamp":"2026-03-31T05:30:00","value":64},{"timestamp":"2026-03-31T05:45:00","value":60},{"timestamp":"2026-03-31T06:00:00","value":64},{"timestamp":"2026-03-31T06:15:00","value":58},{"timestamp":"2026-03-31T06:30:00","value":61},{"timestamp":"2026-03-31T06:45:00","value":68},{"timestamp":"2026-03-31T07:00:00","value":71},{"timestamp":"2026-03-31T07:15:00","value":76},{"timestamp":"2026-03-31T07:30:00","value":67},{"timestamp":"2026-03-31T07:45:00","value":76},{"timestamp":"2026-03-31T08:00:00","value":76},{"timestamp":"2026-03-31T08:15:00","value":71},{"timestamp":"2026-03-31T08:30:00","value":70},{"timestamp":"2026-03-31T08:45:00","value":79},{"timestamp":"2026-03-31T09:00:00","value":90},{"timestamp":"2026-03-31T09:15:00","value":76},{"timestamp":"2026-03-31T09:30:00","value":81},{"timestamp":"2026-03-31T09:45:00","value":81},{"timestamp":"2026-03-31T10:00:00","value":73},{"timestamp":"2026-03-31T10:15:00","value":71},{"timestamp":"2026-03-31T10:30:00","value":79},{"timestamp":"2026-03-31T10:45:00","value":75},{"timestamp":"2026-03-31T11:00:00","value":73},{"timestamp":"2026-03-31T11:15:00","value":81},{"timestamp":"2026-03-31T11:30:00","value":80},{"timestamp":"2026-03-31T11:45:00","value":77},{"timestamp":"2026-03-31T12:00:00","value":82},{"timestamp":"2026-03-31T12:15:00","value":74},{"timestamp":"2026-03-31T12:30:00","value":84},{"timestamp":"2026-03-31T12:45:00","value":83},{"timestamp":"2026-03-31T13:00:00","value":78},{"timestamp":"2026-03-31T13:15:00","value":84},{"timestamp":"2026-03-31T13:30:00","value":74},{"timestamp":"2026-03-31T13:45:00","value":83},{"timestamp":"2026-03-31T14:00:00","value":78},{"timestamp":"2026-03-31T14:15:00","value":80},{"timestamp":"2026-03-31T14:30:00","value":86},{"timestamp":"2026-03-31T14:45:00","value":86},{"timestamp":"2026-03-31T15:00:00","value":87},{"timestamp":"2026-03-31T15:15:00","value":74},{"timestamp":"2026-03-31T15:30:00","value":83},{"timestamp":"2026-03-31T15:45:00","value":75},{"timestamp":"2026-03-31T16:00:00","value":80},{"timestamp":"2026-03-31T16:15:00","value":86},{"timestamp":"2026-03-31T16:30:00","value":75},{"timestamp":"2026-03-31T16:45:00","value":74},{"timestamp":"2026-03-31T17:00:00","value":98},{"timestamp":"2026-03-31T17:15:00","value":127},{"timestamp":"2026-03-31T17:30:00","value":149},{"timestamp":"2026-03-31T17:45:00","value":144},{"timestamp":"2026-03-31T18:00:00","value":126},{"timestamp":"2026-03-31T18:15:00","value":92},{"timestamp":"2026-03-31T18:30:00","value":78},{"timestamp":"2026-03-31T18:45:00","value":80},{"timestamp":"2026-03-31T19:00:00","value":74},{"timestamp":"2026-03-31T19:15:00","value":82},{"timestamp":"2026-03-31T19:30:00","value":78},{"timestamp":"2026-03-31T19:45:00","value":75},{"timestamp":"2026-03-31T20:00:00","value":79},{"timestamp":"2026-03-31T20:15:00","value":69},{"timestamp":"2026-03-31T20:30:00","value":70},{"timestamp":"2026-03-31T20:45:00","value":70},{"timestamp":"2026-03-31T21:00:00","value":75},{"timestamp":"2026-03-31T21:15:00","value":75},{"timestamp":"2026-03-31T21:30:00","value":77},{"timestamp":"2026-03-31T21:45:00","value":77},{"timestamp":"2026-03-31T22:00:00","value":75},{"timestamp":"2026-03-31T22:15:00","value":77},{"timestamp":"2026-03-31T22:30:00","value":71},{"timestamp":"2026-03-31T22:45:00","value":57},{"timestamp":"2026-03-31T23:00:00","value":63},{"timestamp":"2026-03-31T23:15:00","value":60},{"timestamp":"2026-03-31T23:30:00","value":65},{"timestamp":"2026-03-31T23:45:00","value":65}],"hrvSamples":[{"timestamp":"2026-03-31T02:45:00","value":41},{"timestamp":"2026-03-31T04:15:00","value":40.7}],"hrv":41.8,"restingHeartRate":61,"walkingHeartRateAverage":94},"vitals":{"bloodOxygenSamples":[{"timestamp":"2026-03-31T00:45:00","value":97.6,"percent":97.6},{"timestamp":"2026-03-31T02:00:00","value":96.9,"percent":96.9},{"timestamp":"2026-03-31T03:15:00","value":98,"percent":98},{"timestamp":"2026-03-31T04:30:00","value":97,"percent":97},{"timestamp":"2026-03-31T05:45:00","value":97.6,"percent":97.6},{"timestamp":"2026-03-31T07:00:00","value":97.3,"percent":97.3},{"timestamp":"2026-03-31T15:00:00","value":97.2,"percent":97.2},{"timestamp":"2026-03-31T22:00:00","value":97.8,"percent":97.8}],"respiratoryRateSamples":[{"timestamp":"2026-03-31T00:45:00","value":14.9},{"timestamp":"2026-03-31T02:00:00","value":14.8},{"timestamp":"2026-03-31T03:15:00","value":15.4},{"timestamp":"2026-03-31T04:30:00","value":15.7},{"timestamp":"2026-03-31T05:45:00","value":15.3},{"timestamp":"2026-03-31T07:00:00","value":15.2},{"timestamp":"2026-03-31T15:00:00","value":14.3},{"timestamp":"2026-03-31T22:00:00","value":15.3}],"bloodOxygenPercent":97.4,"bloodOxygenAvg":97.4,"bloodOxygenMin":96.9,"bloodOxygenMax":98,"respiratoryRate":15.1,"respiratoryRateAvg":15.1,"respiratoryRateMin":14.3,"respiratoryRateMax":15.7},"sleep":{"sleepStages":[{"stage":"awake","startDate":"2026-03-31T22:15:00","endDate":"2026-03-31T22:25:00","durationSeconds":598},{"stage":"core","startDate":"2026-03-31T22:25:00","endDate":"2026-03-31T23:13:00","durationSeconds":2864},{"stage":"deep","startDate":"2026-03-31T23:13:00","endDate":"2026-04-01T00:06:00","durationSeconds":3202},{"stage":"core","startDate":"2026-04-01T00:06:00","endDate":"2026-04-01T00:44:00","durationSeconds":2289},{"stage":"rem","startDate":"2026-04-01T00:44:00","endDate":"2026-04-01T01:00:00","durationSeconds":927},{"stage":"awake","startDate":"2026-04-01T01:00:00","endDate":"2026-04-01T01:02:00","durationSeconds":164},{"stage":"core","startDate":"2026-04-01T01:02:00","endDate":"2026-04-01T02:06:00","durationSeconds":3808},{"stage":"deep","startDate":"2026-04-01T02:06:00","endDate":"2026-04-01T02:38:00","durationSeconds":1903},{"stage":"core","startDate":"2026-04-01T02:38:00","endDate":"2026-04-01T03:23:00","durationSeconds":2742},{"stage":"rem","startDate":"2026-04-01T03:23:00","endDate":"2026-04-01T03:59:00","durationSeconds":2123},{"stage":"awake","startDate":"2026-04-01T03:59:00","endDate":"2026-04-01T04:03:00","durationSeconds":268},{"stage":"core","startDate":"2026-04-01T04:03:00","endDate":"2026-04-01T05:28:00","durationSeconds":5083},{"stage":"deep","startDate":"2026-04-01T05:28:00","endDate":"2026-04-01T05:44:00","durationSeconds":959},{"stage":"core","startDate":"2026-04-01T05:44:00","endDate":"2026-04-01T05:56:00","durationSeconds":744},{"stage":"awake","startDate":"2026-04-01T05:56:00","endDate":"2026-04-01T06:00:00","durationSeconds":237},{"stage":"awake","startDate":"2026-04-01T06:00:00","endDate":"2026-04-01T06:21:00","durationSeconds":1253}],"totalDuration":26644,"totalDurationFormatted":"7h 24m","deepSleep":6064,"deepSleepFormatted":"1h 41m","remSleep":3050,"remSleepFormatted":"51m","coreSleep":17530,"coreSleepFormatted":"4h 52m","awakeTime":2520,"awakeTimeFormatted":"42m","bedtime":"2026-03-31T22:15:00","wakeTime":"2026-04-01T06:21:00"},"mobility":{"walkingSpeed":1.23,"walkingAsymmetryPercentage":1.7,"walkingStepLength":0.78,"walkingDoubleSupportPercentage":25.4,"stairAscentSpeed":0.5,"stairDescentSpeed":0.64},"hearing":{"headphoneAudioLevel":58.7},"workouts":[{"type":"high intensity interval training","duration":2812,"durationFormatted":"47m","calories":495,"startTime":"2026-03-31T17:12:00","avgHeartRate":155,"maxHeartRate":177,"minHeartRate":83,"timeSeries":{"heartRate":[{"timestamp":"2026-03-31T17:12:00","value":83},{"timestamp":"2026-03-31T17:13:00","value":93},{"timestamp":"2026-03-31T17:14:00","value":110},{"timestamp":"2026-03-31T17:15:00","value":117},{"timestamp":"2026-03-31T17:16:00","value":127},{"timestamp":"2026-03-31T17:17:00","value":132},{"timestamp":"2026-03-31T17:18:00","value":138},{"timestamp":"2026-03-31T17:19:00","value":150},{"timestamp":"2026-03-31T17:20:00","value":161},{"timestamp":"2026-03-31T17:21:00","value":170},{"timestamp":"2026-03-31T17:22:00","value":173},{"timestamp":"2026-03-31T17:23:00","value":174},{"timestamp":"2026-03-31T17:24:00","value":174},{"timestamp":"2026-03-31T17:25:00","value":171},{"timestamp":"2026-03-31T17:26:00","value":173},{"timestamp":"2026-03-31T17:27:00","value":167},{"timestamp":"2026-03-31T17:28:00","value":168},{"timestamp":"2026-03-31T17:29:00","value":165},{"timestamp":"2026-03-31T17:30:00","value":168},{"timestamp":"2026-03-31T17:31:00","value":174},{"timestamp":"2026-03-31T17:32:00","value":171},{"timestamp":"2026-03-31T17:33:00","value":176},{"timestamp":"2026-03-31T17:34:00","value":171},{"timestamp":"2026-03-31T17:35:00","value":173},{"timestamp":"2026-03-31T17:36:00","value":169},{"timestamp":"2026-03-31T17:37:00","value":168},{"timestamp":"2026-03-31T17:38:00","value":170},{"timestamp":"2026-03-31T17:39:00","value":168},{"timestamp":"2026-03-31T17:40:00","value":176},{"timestamp":"2026-03-31T17:41:00","value":175},{"timestamp":"2026-03-31T17:42:00","value":172},{"timestamp":"2026-03-31T17:43:00","value":175},{"timestamp":"2026-03-31T17:44:00","value":174},{"timestamp":"2026-03-31T17:45:00","value":172},{"timestamp":"2026-03-31T17:46:00","value":170},{"timestamp":"2026-03-31T17:47:00","value":168},{"timestamp":"2026-03-31T17:48:00","value":168},{"timestamp":"2026-03-31T17:49:00","value":171},{"timestamp":"2026-03-31T17:50:00","value":174},{"timestamp":"2026-03-31T17:51:00","value":177},{"timestamp":"2026-03-31T17:52:00","value":164},{"timestamp":"2026-03-31T17:53:00","value":149},{"timestamp":"2026-03-31T17:54:00","value":135},{"timestamp":"2026-03-31T17:55:00","value":121},{"timestamp":"2026-03-31T17:56:00","value":105},{"timestamp":"2026-03-31T17:57:00","value":93},{"timestamp":"2026-03-31T17:58:00","value":83}]},"distance":7.74,"distanceFormatted":"7.74 km","avgPaceFormatted":"6:03/km","avgSpeedFormatted":"9.9 km/h","route":[{"timestamp":"2026-03-31T17:12:00","latitude":37.767387,"longitude":-122.477444,"altitude":46.5,"speedMps":2.68,"courseDegrees":2,"horizontalAccuracyMeters":3.6},{"timestamp":"2026-03-31T17:13:00","latitude":37.768379,"longitude":-122.477086,"altitude":54.2,"speedMps":2.98,"courseDegrees":9,"horizontalAccuracyMeters":7},{"timestamp":"2026-03-31T17:15:00","latitude":37.770636,"longitude":-122.477794,"altitude":56.7,"speedMps":2.46,"courseDegrees":26,"horizontalAccuracyMeters":6.9},{"timestamp":"2026-03-31T17:16:00","latitude":37.771732,"longitude":-122.478994,"altitude":63.4,"speedMps":2.36,"courseDegrees":37,"horizontalAccuracyMeters":4.7},{"timestamp":"2026-03-31T17:18:00","latitude":37.771967,"longitude":-122.480169,"altitude":61.3,"speedMps":3.05,"courseDegrees":44,"horizontalAccuracyMeters":4.9},{"timestamp":"2026-03-31T17:19:00","latitude":37.772575,"longitude":-122.482174,"altitude":61,"speedMps":2.41,"courseDegrees":61,"horizontalAccuracyMeters":4.6},{"timestamp":"2026-03-31T17:21:00","latitude":37.772603,"longitude":-122.483374,"altitude":57.5,"speedMps":2.52,"courseDegrees":72,"horizontalAccuracyMeters":4.5},{"timestamp":"2026-03-31T17:22:00","latitude":37.772881,"longitude":-122.48475,"altitude":48,"speedMps":2.63,"courseDegrees":86,"horizontalAccuracyMeters":4},{"timestamp":"2026-03-31T17:24:00","latitude":37.773352,"longitude":-122.485479,"altitude":41.1,"speedMps":2.76,"courseDegrees":93,"horizontalAccuracyMeters":6.4},{"timestamp":"2026-03-31T17:26:00","latitude":37.773606,"longitude":-122.48777,"altitude":32.9,"speedMps":2.81,"courseDegrees":112,"horizontalAccuracyMeters":5.7},{"timestamp":"2026-03-31T17:27:00","latitude":37.773733,"longitude":-122.489176,"altitude":28.3,"speedMps":2.32,"courseDegrees":121,"horizontalAccuracyMeters":4.4},{"timestamp":"2026-03-31T17:29:00","latitude":37.772804,"longitude":-122.49107,"altitude":28.1,"speedMps":2.75,"courseDegrees":136,"horizontalAccuracyMeters":6.4},{"timestamp":"2026-03-31T17:30:00","latitude":37.771665,"longitude":-122.491988,"altitude":28.7,"speedMps":2.3,"courseDegrees":146,"horizontalAccuracyMeters":7.6},{"timestamp":"2026-03-31T17:32:00","latitude":37.770521,"longitude":-122.492119,"altitude":31.5,"speedMps":2.51,"courseDegrees":154,"horizontalAccuracyMeters":8.2},{"timestamp":"2026-03-31T17:33:00","latitude":37.768531,"longitude":-122.492029,"altitude":37.8,"speedMps":2.41,"courseDegrees":168,"horizontalAccuracyMeters":6.7},{"timestamp":"2026-03-31T17:35:00","latitude":37.766736,"longitude":-122.491429,"altitude":45.8,"speedMps":2.42,"courseDegrees":183,"horizontalAccuracyMeters":5.7},{"timestamp":"2026-03-31T17:36:00","latitude":37.765674,"longitude":-122.490808,"altitude":52.9,"speedMps":2.88,"courseDegrees":194,"horizontalAccuracyMeters":6.7},{"timestamp":"2026-03-31T17:38:00","latitude":37.764528,"longitude":-122.490391,"altitude":57.5,"speedMps":3.08,"courseDegrees":206,"horizontalAccuracyMeters":4.1},{"timestamp":"2026-03-31T17:40:00","latitude":37.763264,"longitude":-122.490143,"altitude":61,"speedMps":3.14,"courseDegrees":218,"horizontalAccuracyMeters":7.6},{"timestamp":"2026-03-31T17:41:00","latitude":37.761951,"longitude":-122.489943,"altitude":62.3,"speedMps":3.15,"courseDegrees":227,"horizontalAccuracyMeters":5.7},{"timestamp":"2026-03-31T17:43:00","latitude":37.760572,"longitude":-122.489364,"altitude":61.9,"speedMps":2.46,"courseDegrees":237,"horizontalAccuracyMeters":3.5},{"timestamp":"2026-03-31T17:44:00","latitude":37.759361,"longitude":-122.487913,"altitude":54.8,"speedMps":3.14,"courseDegrees":251,"horizontalAccuracyMeters":5.9},{"timestamp":"2026-03-31T17:46:00","latitude":37.758958,"longitude":-122.486179,"altitude":47.3,"speedMps":3.03,"courseDegrees":263,"horizontalAccuracyMeters":6.9},{"timestamp":"2026-03-31T17:47:00","latitude":37.759379,"longitude":-122.484628,"altitude":41.7,"speedMps":2.52,"courseDegrees":274,"horizontalAccuracyMeters":7.6},{"timestamp":"2026-03-31T17:49:00","latitude":37.760356,"longitude":-122.48331,"altitude":33.1,"speedMps":2.39,"courseDegrees":286,"horizontalAccuracyMeters":5.6},{"timestamp":"2026-03-31T17:51:00","latitude":37.761884,"longitude":-122.481725,"altitude":29.7,"speedMps":2.31,"courseDegrees":304,"horizontalAccuracyMeters":7.1},{"timestamp":"2026-03-31T17:52:00","latitude":37.762523,"longitude":-122.481615,"altitude":28.2,"speedMps":3.23,"courseDegrees":308,"horizontalAccuracyMeters":5.5},{"timestamp":"2026-03-31T17:54:00","latitude":37.763833,"longitude":-122.480384,"altitude":28.4,"speedMps":2.73,"courseDegrees":326,"horizontalAccuracyMeters":6.5},{"timestamp":"2026-03-31T17:55:00","latitude":37.76473,"longitude":-122.479383,"altitude":30.7,"speedMps":2.44,"courseDegrees":338,"horizontalAccuracyMeters":6.1},{"timestamp":"2026-03-31T17:57:00","latitude":37.765866,"longitude":-122.478286,"altitude":39.2,"speedMps":2.53,"courseDegrees":350,"horizontalAccuracyMeters":6.3},{"timestamp":"2026-03-31T17:58:00","latitude":37.767515,"longitude":-122.47745,"altitude":43.2,"speedMps":2.26,"courseDegrees":3,"horizontalAccuracyMeters":4.7}],"splits":[{"index":1,"duration":419,"distance":1,"paceFormatted":"6:28/km","avgHeartRate":155},{"index":2,"duration":417,"distance":1,"paceFormatted":"6:48/km","avgHeartRate":159},{"index":3,"duration":417,"distance":1,"paceFormatted":"6:41/km","avgHeartRate":155},{"index":4,"duration":384,"distance":1,"paceFormatted":"6:58/km","avgHeartRate":158},{"index":5,"duration":395,"distance":1,"paceFormatted":"6:44/km","avgHeartRate":155},{"index":6,"duration":387,"distance":1,"paceFormatted":"6:59/km","avgHeartRate":158},{"index":7,"duration":396,"distance":1,"paceFormatted":"6:45/km","avgHeartRate":152}]}]}
