{"type":"health-data","date":"2026-04-25","units":"metric","activity":{"steps":11561,"walkingRunningDistanceKm":9.43,"walkingRunningDistance":9430,"activeCalories":888,"exerciseMinutes":66,"vo2Max":42.4,"basalEnergyBurned":1560,"standHours":14,"flightsClimbed":5},"heart":{"averageHeartRate":74.4,"heartRateMin":56,"heartRateMax":142,"heartRateSamples":[{"timestamp":"2026-04-25T00:00:00","value":59},{"timestamp":"2026-04-25T00:15:00","value":61},{"timestamp":"2026-04-25T00:30:00","value":56},{"timestamp":"2026-04-25T00:45:00","value":56},{"timestamp":"2026-04-25T01:00:00","value":59},{"timestamp":"2026-04-25T01:15:00","value":62},{"timestamp":"2026-04-25T01:30:00","value":64},{"timestamp":"2026-04-25T01:45:00","value":60},{"timestamp":"2026-04-25T02:00:00","value":60},{"timestamp":"2026-04-25T02:15:00","value":57},{"timestamp":"2026-04-25T02:30:00","value":62},{"timestamp":"2026-04-25T02:45:00","value":58},{"timestamp":"2026-04-25T03:00:00","value":60},{"timestamp":"2026-04-25T03:15:00","value":60},{"timestamp":"2026-04-25T03:30:00","value":63},{"timestamp":"2026-04-25T03:45:00","value":61},{"timestamp":"2026-04-25T04:00:00","value":58},{"timestamp":"2026-04-25T04:15:00","value":64},{"timestamp":"2026-04-25T04:30:00","value":64},{"timestamp":"2026-04-25T04:45:00","value":59},{"timestamp":"2026-04-25T05:00:00","value":56},{"timestamp":"2026-04-25T05:15:00","value":63},{"timestamp":"2026-04-25T05:30:00","value":62},{"timestamp":"2026-04-25T05:45:00","value":63},{"timestamp":"2026-04-25T06:00:00","value":61},{"timestamp":"2026-04-25T06:15:00","value":64},{"timestamp":"2026-04-25T06:30:00","value":60},{"timestamp":"2026-04-25T06:45:00","value":67},{"timestamp":"2026-04-25T07:00:00","value":70},{"timestamp":"2026-04-25T07:15:00","value":73},{"timestamp":"2026-04-25T07:30:00","value":74},{"timestamp":"2026-04-25T07:45:00","value":68},{"timestamp":"2026-04-25T08:00:00","value":71},{"timestamp":"2026-04-25T08:15:00","value":78},{"timestamp":"2026-04-25T08:30:00","value":72},{"timestamp":"2026-04-25T08:45:00","value":101},{"timestamp":"2026-04-25T09:00:00","value":123},{"timestamp":"2026-04-25T09:15:00","value":141},{"timestamp":"2026-04-25T09:30:00","value":142},{"timestamp":"2026-04-25T09:45:00","value":130},{"timestamp":"2026-04-25T10:00:00","value":110},{"timestamp":"2026-04-25T10:15:00","value":94},{"timestamp":"2026-04-25T10:30:00","value":75},{"timestamp":"2026-04-25T10:45:00","value":73},{"timestamp":"2026-04-25T11:00:00","value":79},{"timestamp":"2026-04-25T11:15:00","value":74},{"timestamp":"2026-04-25T11:30:00","value":80},{"timestamp":"2026-04-25T11:45:00","value":82},{"timestamp":"2026-04-25T12:00:00","value":83},{"timestamp":"2026-04-25T12:15:00","value":78},{"timestamp":"2026-04-25T12:30:00","value":73},{"timestamp":"2026-04-25T12:45:00","value":84},{"timestamp":"2026-04-25T13:00:00","value":75},{"timestamp":"2026-04-25T13:15:00","value":84},{"timestamp":"2026-04-25T13:30:00","value":84},{"timestamp":"2026-04-25T13:45:00","value":78},{"timestamp":"2026-04-25T14:00:00","value":80},{"timestamp":"2026-04-25T14:15:00","value":85},{"timestamp":"2026-04-25T14:30:00","value":78},{"timestamp":"2026-04-25T14:45:00","value":83},{"timestamp":"2026-04-25T15:00:00","value":85},{"timestamp":"2026-04-25T15:15:00","value":77},{"timestamp":"2026-04-25T15:30:00","value":76},{"timestamp":"2026-04-25T15:45:00","value":78},{"timestamp":"2026-04-25T16:00:00","value":86},{"timestamp":"2026-04-25T16:15:00","value":79},{"timestamp":"2026-04-25T16:30:00","value":85},{"timestamp":"2026-04-25T16:45:00","value":75},{"timestamp":"2026-04-25T17:00:00","value":73},{"timestamp":"2026-04-25T17:15:00","value":79},{"timestamp":"2026-04-25T17:30:00","value":78},{"timestamp":"2026-04-25T17:45:00","value":75},{"timestamp":"2026-04-25T18:00:00","value":86},{"timestamp":"2026-04-25T18:15:00","value":83},{"timestamp":"2026-04-25T18:30:00","value":73},{"timestamp":"2026-04-25T18:45:00","value":72},{"timestamp":"2026-04-25T19:00:00","value":70},{"timestamp":"2026-04-25T19:15:00","value":74},{"timestamp":"2026-04-25T19:30:00","value":76},{"timestamp":"2026-04-25T19:45:00","value":82},{"timestamp":"2026-04-25T20:00:00","value":77},{"timestamp":"2026-04-25T20:15:00","value":76},{"timestamp":"2026-04-25T20:30:00","value":71},{"timestamp":"2026-04-25T20:45:00","value":76},{"timestamp":"2026-04-25T21:00:00","value":87},{"timestamp":"2026-04-25T21:15:00","value":69},{"timestamp":"2026-04-25T21:30:00","value":71},{"timestamp":"2026-04-25T21:45:00","value":68},{"timestamp":"2026-04-25T22:00:00","value":70},{"timestamp":"2026-04-25T22:15:00","value":76},{"timestamp":"2026-04-25T22:30:00","value":76},{"timestamp":"2026-04-25T22:45:00","value":64},{"timestamp":"2026-04-25T23:00:00","value":57},{"timestamp":"2026-04-25T23:15:00","value":56},{"timestamp":"2026-04-25T23:30:00","value":57},{"timestamp":"2026-04-25T23:45:00","value":57}],"hrvSamples":[{"timestamp":"2026-04-25T02:45:00","value":45.7},{"timestamp":"2026-04-25T04:15:00","value":44.5}],"hrv":44.2,"restingHeartRate":60,"walkingHeartRateAverage":90},"vitals":{"bloodOxygenSamples":[{"timestamp":"2026-04-25T00:45:00","value":98.6,"percent":98.6},{"timestamp":"2026-04-25T02:00:00","value":98.2,"percent":98.2},{"timestamp":"2026-04-25T03:15:00","value":97.7,"percent":97.7},{"timestamp":"2026-04-25T04:30:00","value":97.7,"percent":97.7},{"timestamp":"2026-04-25T05:45:00","value":98.6,"percent":98.6},{"timestamp":"2026-04-25T07:00:00","value":98.3,"percent":98.3},{"timestamp":"2026-04-25T15:00:00","value":98.4,"percent":98.4},{"timestamp":"2026-04-25T22:00:00","value":98.5,"percent":98.5}],"respiratoryRateSamples":[{"timestamp":"2026-04-25T00:45:00","value":14.8},{"timestamp":"2026-04-25T02:00:00","value":14.1},{"timestamp":"2026-04-25T03:15:00","value":15.3},{"timestamp":"2026-04-25T04:30:00","value":14.1},{"timestamp":"2026-04-25T05:45:00","value":14.8},{"timestamp":"2026-04-25T07:00:00","value":14.2},{"timestamp":"2026-04-25T15:00:00","value":14},{"timestamp":"2026-04-25T22:00:00","value":14.9}],"bloodOxygenPercent":98.2,"bloodOxygenAvg":98.2,"bloodOxygenMin":97.7,"bloodOxygenMax":98.6,"respiratoryRate":14.5,"respiratoryRateAvg":14.5,"respiratoryRateMin":14,"respiratoryRateMax":15.3},"sleep":{"sleepStages":[{"stage":"awake","startDate":"2026-04-25T23:15:00","endDate":"2026-04-25T23:23:00","durationSeconds":445},{"stage":"core","startDate":"2026-04-25T23:23:00","endDate":"2026-04-26T00:15:00","durationSeconds":3129},{"stage":"deep","startDate":"2026-04-26T00:15:00","endDate":"2026-04-26T01:04:00","durationSeconds":2959},{"stage":"core","startDate":"2026-04-26T01:04:00","endDate":"2026-04-26T01:37:00","durationSeconds":1954},{"stage":"rem","startDate":"2026-04-26T01:37:00","endDate":"2026-04-26T01:55:00","durationSeconds":1086},{"stage":"awake","startDate":"2026-04-26T01:55:00","endDate":"2026-04-26T02:00:00","durationSeconds":313},{"stage":"core","startDate":"2026-04-26T02:00:00","endDate":"2026-04-26T03:10:00","durationSeconds":4194},{"stage":"deep","startDate":"2026-04-26T03:10:00","endDate":"2026-04-26T03:44:00","durationSeconds":2027},{"stage":"core","startDate":"2026-04-26T03:44:00","endDate":"2026-04-26T04:40:00","durationSeconds":3357},{"stage":"rem","startDate":"2026-04-26T04:40:00","endDate":"2026-04-26T05:18:00","durationSeconds":2267},{"stage":"awake","startDate":"2026-04-26T05:18:00","endDate":"2026-04-26T05:22:00","durationSeconds":248},{"stage":"core","startDate":"2026-04-26T05:22:00","endDate":"2026-04-26T06:50:00","durationSeconds":5326},{"stage":"deep","startDate":"2026-04-26T06:50:00","endDate":"2026-04-26T07:03:00","durationSeconds":731},{"stage":"core","startDate":"2026-04-26T07:03:00","endDate":"2026-04-26T07:36:00","durationSeconds":2010},{"stage":"awake","startDate":"2026-04-26T07:36:00","endDate":"2026-04-26T07:38:00","durationSeconds":96},{"stage":"awake","startDate":"2026-04-26T07:38:00","endDate":"2026-04-26T07:50:00","durationSeconds":736}],"totalDuration":29040,"totalDurationFormatted":"8h 4m","deepSleep":5717,"deepSleepFormatted":"1h 35m","remSleep":3353,"remSleepFormatted":"56m","coreSleep":19970,"coreSleepFormatted":"5h 33m","awakeTime":1838,"awakeTimeFormatted":"31m","bedtime":"2026-04-25T23:15:00","wakeTime":"2026-04-26T07:50:00"},"mobility":{"walkingSpeed":1.31,"walkingAsymmetryPercentage":2,"walkingStepLength":0.74,"walkingDoubleSupportPercentage":26,"stairAscentSpeed":0.53,"stairDescentSpeed":0.65},"hearing":{"headphoneAudioLevel":63.7},"workouts":[{"type":"cycling","duration":4220,"durationFormatted":"1h 10m","calories":608,"startTime":"2026-04-25T08:51:00","avgHeartRate":138,"maxHeartRate":155,"minHeartRate":84,"timeSeries":{"heartRate":[{"timestamp":"2026-04-25T08:51:00","value":85},{"timestamp":"2026-04-25T08:52:00","value":88},{"timestamp":"2026-04-25T08:53:00","value":96},{"timestamp":"2026-04-25T08:54:00","value":102},{"timestamp":"2026-04-25T08:55:00","value":108},{"timestamp":"2026-04-25T08:56:00","value":117},{"timestamp":"2026-04-25T08:57:00","value":118},{"timestamp":"2026-04-25T08:58:00","value":121},{"timestamp":"2026-04-25T08:59:00","value":124},{"timestamp":"2026-04-25T09:00:00","value":130},{"timestamp":"2026-04-25T09:01:00","value":135},{"timestamp":"2026-04-25T09:02:00","value":140},{"timestamp":"2026-04-25T09:03:00","value":143},{"timestamp":"2026-04-25T09:04:00","value":150},{"timestamp":"2026-04-25T09:05:00","value":154},{"timestamp":"2026-04-25T09:06:00","value":152},{"timestamp":"2026-04-25T09:07:00","value":154},{"timestamp":"2026-04-25T09:08:00","value":155},{"timestamp":"2026-04-25T09:09:00","value":155},{"timestamp":"2026-04-25T09:10:00","value":153},{"timestamp":"2026-04-25T09:11:00","value":155},{"timestamp":"2026-04-25T09:12:00","value":150},{"timestamp":"2026-04-25T09:13:00","value":151},{"timestamp":"2026-04-25T09:14:00","value":147},{"timestamp":"2026-04-25T09:15:00","value":149},{"timestamp":"2026-04-25T09:16:00","value":145},{"timestamp":"2026-04-25T09:17:00","value":147},{"timestamp":"2026-04-25T09:18:00","value":150},{"timestamp":"2026-04-25T09:19:00","value":150},{"timestamp":"2026-04-25T09:20:00","value":152},{"timestamp":"2026-04-25T09:21:00","value":155},{"timestamp":"2026-04-25T09:22:00","value":154},{"timestamp":"2026-04-25T09:23:00","value":150},{"timestamp":"2026-04-25T09:24:00","value":152},{"timestamp":"2026-04-25T09:25:00","value":153},{"timestamp":"2026-04-25T09:26:00","value":154},{"timestamp":"2026-04-25T09:27:00","value":152},{"timestamp":"2026-04-25T09:28:00","value":150},{"timestamp":"2026-04-25T09:29:00","value":144},{"timestamp":"2026-04-25T09:30:00","value":147},{"timestamp":"2026-04-25T09:31:00","value":146},{"timestamp":"2026-04-25T09:32:00","value":149},{"timestamp":"2026-04-25T09:33:00","value":149},{"timestamp":"2026-04-25T09:34:00","value":155},{"timestamp":"2026-04-25T09:35:00","value":152},{"timestamp":"2026-04-25T09:36:00","value":155},{"timestamp":"2026-04-25T09:37:00","value":153},{"timestamp":"2026-04-25T09:38:00","value":155},{"timestamp":"2026-04-25T09:39:00","value":153},{"timestamp":"2026-04-25T09:40:00","value":150},{"timestamp":"2026-04-25T09:41:00","value":148},{"timestamp":"2026-04-25T09:42:00","value":151},{"timestamp":"2026-04-25T09:43:00","value":146},{"timestamp":"2026-04-25T09:44:00","value":146},{"timestamp":"2026-04-25T09:45:00","value":151},{"timestamp":"2026-04-25T09:46:00","value":152},{"timestamp":"2026-04-25T09:47:00","value":150},{"timestamp":"2026-04-25T09:48:00","value":151},{"timestamp":"2026-04-25T09:49:00","value":150},{"timestamp":"2026-04-25T09:50:00","value":148},{"timestamp":"2026-04-25T09:51:00","value":146},{"timestamp":"2026-04-25T09:52:00","value":142},{"timestamp":"2026-04-25T09:53:00","value":129},{"timestamp":"2026-04-25T09:54:00","value":121},{"timestamp":"2026-04-25T09:55:00","value":113},{"timestamp":"2026-04-25T09:56:00","value":106},{"timestamp":"2026-04-25T09:57:00","value":100},{"timestamp":"2026-04-25T09:58:00","value":93},{"timestamp":"2026-04-25T09:59:00","value":87},{"timestamp":"2026-04-25T10:00:00","value":84},{"timestamp":"2026-04-25T10:01:00","value":85}]},"distance":27.6,"distanceFormatted":"27.60 km","avgPaceFormatted":"2:33/km","avgSpeedFormatted":"23.5 km/h","route":[{"timestamp":"2026-04-25T08:51:00","latitude":37.770546,"longitude":-122.471169,"altitude":44.7,"speedMps":5.7,"courseDegrees":1,"horizontalAccuracyMeters":6.6},{"timestamp":"2026-04-25T08:52:00","latitude":37.772555,"longitude":-122.47263,"altitude":50.3,"speedMps":6.74,"courseDegrees":8,"horizontalAccuracyMeters":5.1},{"timestamp":"2026-04-25T08:54:00","latitude":37.775129,"longitude":-122.474351,"altitude":54.6,"speedMps":5.8,"courseDegrees":19,"horizontalAccuracyMeters":4.7},{"timestamp":"2026-04-25T08:55:00","latitude":37.776208,"longitude":-122.475513,"altitude":56.6,"speedMps":7.01,"courseDegrees":24,"horizontalAccuracyMeters":7.1},{"timestamp":"2026-04-25T08:57:00","latitude":37.778244,"longitude":-122.476836,"altitude":61.3,"speedMps":6.95,"courseDegrees":33,"horizontalAccuracyMeters":4.6},{"timestamp":"2026-04-25T08:58:00","latitude":37.78016,"longitude":-122.477863,"altitude":61.2,"speedMps":7.41,"courseDegrees":41,"horizontalAccuracyMeters":8.6},{"timestamp":"2026-04-25T09:00:00","latitude":37.781527,"longitude":-122.478025,"altitude":61.2,"speedMps":6.01,"courseDegrees":46,"horizontalAccuracyMeters":8.2},{"timestamp":"2026-04-25T09:01:00","latitude":37.783746,"longitude":-122.478808,"altitude":60.2,"speedMps":7.71,"courseDegrees":53,"horizontalAccuracyMeters":7.1},{"timestamp":"2026-04-25T09:03:00","latitude":37.786205,"longitude":-122.480156,"altitude":58,"speedMps":7.41,"courseDegrees":61,"horizontalAccuracyMeters":6.8},{"timestamp":"2026-04-25T09:04:00","latitude":37.789047,"longitude":-122.483735,"altitude":58.2,"speedMps":6.06,"courseDegrees":74,"horizontalAccuracyMeters":4.3},{"timestamp":"2026-04-25T09:06:00","latitude":37.790135,"longitude":-122.484036,"altitude":52.6,"speedMps":6.6,"courseDegrees":76,"horizontalAccuracyMeters":5.2},{"timestamp":"2026-04-25T09:07:00","latitude":37.791237,"longitude":-122.487273,"altitude":46,"speedMps":6.08,"courseDegrees":85,"horizontalAccuracyMeters":7.9},{"timestamp":"2026-04-25T09:09:00","latitude":37.791189,"longitude":-122.49167,"altitude":44.3,"speedMps":6.59,"courseDegrees":97,"horizontalAccuracyMeters":8.8},{"timestamp":"2026-04-25T09:10:00","latitude":37.790103,"longitude":-122.494583,"altitude":38.5,"speedMps":7.67,"courseDegrees":105,"horizontalAccuracyMeters":3.7},{"timestamp":"2026-04-25T09:12:00","latitude":37.78904,"longitude":-122.494826,"altitude":34,"speedMps":6.41,"courseDegrees":107,"horizontalAccuracyMeters":3.9},{"timestamp":"2026-04-25T09:13:00","latitude":37.785954,"longitude":-122.498756,"altitude":30.5,"speedMps":6.86,"courseDegrees":121,"horizontalAccuracyMeters":4.2},{"timestamp":"2026-04-25T09:15:00","latitude":37.784185,"longitude":-122.499058,"altitude":26.2,"speedMps":7.69,"courseDegrees":125,"horizontalAccuracyMeters":7.9},{"timestamp":"2026-04-25T09:16:00","latitude":37.781371,"longitude":-122.500569,"altitude":28.6,"speedMps":5.54,"courseDegrees":135,"horizontalAccuracyMeters":7.5},{"timestamp":"2026-04-25T09:18:00","latitude":37.779483,"longitude":-122.501111,"altitude":28.9,"speedMps":6.74,"courseDegrees":142,"horizontalAccuracyMeters":5},{"timestamp":"2026-04-25T09:20:00","latitude":37.777273,"longitude":-122.502132,"altitude":27.9,"speedMps":7.03,"courseDegrees":151,"horizontalAccuracyMeters":6.9},{"timestamp":"2026-04-25T09:21:00","latitude":37.776768,"longitude":-122.502586,"altitude":33.5,"speedMps":7.34,"courseDegrees":154,"horizontalAccuracyMeters":4.6},{"timestamp":"2026-04-25T09:23:00","latitude":37.77523,"longitude":-122.503958,"altitude":34.1,"speedMps":7.58,"courseDegrees":161,"horizontalAccuracyMeters":7.8},{"timestamp":"2026-04-25T09:24:00","latitude":37.773441,"longitude":-122.505549,"altitude":39.5,"speedMps":6.89,"courseDegrees":169,"horizontalAccuracyMeters":8.5},{"timestamp":"2026-04-25T09:26:00","latitude":37.77107,"longitude":-122.507141,"altitude":46.5,"speedMps":5.81,"courseDegrees":177,"horizontalAccuracyMeters":6.1},{"timestamp":"2026-04-25T09:27:00","latitude":37.768135,"longitude":-122.508351,"altitude":51.3,"speedMps":5.78,"courseDegrees":186,"horizontalAccuracyMeters":3.5},{"timestamp":"2026-04-25T09:29:00","latitude":37.76502,"longitude":-122.508881,"altitude":53.9,"speedMps":5.46,"courseDegrees":195,"horizontalAccuracyMeters":5.2},{"timestamp":"2026-04-25T09:30:00","latitude":37.762164,"longitude":-122.508657,"altitude":56.5,"speedMps":5.84,"courseDegrees":202,"horizontalAccuracyMeters":8.9},{"timestamp":"2026-04-25T09:32:00","latitude":37.759849,"longitude":-122.507755,"altitude":60.8,"speedMps":6.79,"courseDegrees":209,"horizontalAccuracyMeters":5.1},{"timestamp":"2026-04-25T09:33:00","latitude":37.757314,"longitude":-122.505664,"altitude":61.5,"speedMps":5.5,"courseDegrees":218,"horizontalAccuracyMeters":6.5},{"timestamp":"2026-04-25T09:35:00","latitude":37.75538,"longitude":-122.502763,"altitude":62,"speedMps":7.08,"courseDegrees":227,"horizontalAccuracyMeters":6.3},{"timestamp":"2026-04-25T09:36:00","latitude":37.754057,"longitude":-122.499087,"altitude":61.3,"speedMps":7.44,"courseDegrees":238,"horizontalAccuracyMeters":7.8},{"timestamp":"2026-04-25T09:38:00","latitude":37.754786,"longitude":-122.497731,"altitude":58,"speedMps":7.37,"courseDegrees":241,"horizontalAccuracyMeters":3.9},{"timestamp":"2026-04-25T09:39:00","latitude":37.755104,"longitude":-122.495542,"altitude":58.3,"speedMps":5.38,"courseDegrees":247,"horizontalAccuracyMeters":3.9},{"timestamp":"2026-04-25T09:41:00","latitude":37.754934,"longitude":-122.491297,"altitude":51.2,"speedMps":7.35,"courseDegrees":262,"horizontalAccuracyMeters":6.2},{"timestamp":"2026-04-25T09:42:00","latitude":37.755345,"longitude":-122.489973,"altitude":47.7,"speedMps":5.54,"courseDegrees":267,"horizontalAccuracyMeters":8.9},{"timestamp":"2026-04-25T09:44:00","latitude":37.755461,"longitude":-122.48726,"altitude":41.1,"speedMps":5.67,"courseDegrees":277,"horizontalAccuracyMeters":4.4},{"timestamp":"2026-04-25T09:46:00","latitude":37.75496,"longitude":-122.487118,"altitude":36.8,"speedMps":6.32,"courseDegrees":278,"horizontalAccuracyMeters":6},{"timestamp":"2026-04-25T09:47:00","latitude":37.754696,"longitude":-122.484046,"altitude":34.2,"speedMps":5.83,"courseDegrees":288,"horizontalAccuracyMeters":7.4},{"timestamp":"2026-04-25T09:49:00","latitude":37.754955,"longitude":-122.480456,"altitude":29.8,"speedMps":7.43,"courseDegrees":300,"horizontalAccuracyMeters":6.6},{"timestamp":"2026-04-25T09:50:00","latitude":37.755288,"longitude":-122.477605,"altitude":29.1,"speedMps":5.83,"courseDegrees":308,"horizontalAccuracyMeters":4.4},{"timestamp":"2026-04-25T09:52:00","latitude":37.755557,"longitude":-122.475485,"altitude":26.9,"speedMps":6.74,"courseDegrees":313,"horizontalAccuracyMeters":5.4},{"timestamp":"2026-04-25T09:53:00","latitude":37.756035,"longitude":-122.473832,"altitude":29,"speedMps":6.92,"courseDegrees":317,"horizontalAccuracyMeters":4.1},{"timestamp":"2026-04-25T09:55:00","latitude":37.758834,"longitude":-122.471231,"altitude":29.8,"speedMps":6.54,"courseDegrees":328,"horizontalAccuracyMeters":5.5},{"timestamp":"2026-04-25T09:56:00","latitude":37.761906,"longitude":-122.469812,"altitude":32.7,"speedMps":6.69,"courseDegrees":337,"horizontalAccuracyMeters":8},{"timestamp":"2026-04-25T09:58:00","latitude":37.765636,"longitude":-122.469313,"altitude":37.1,"speedMps":6.28,"courseDegrees":347,"horizontalAccuracyMeters":5},{"timestamp":"2026-04-25T09:59:00","latitude":37.76849,"longitude":-122.469948,"altitude":40.2,"speedMps":7.12,"courseDegrees":355,"horizontalAccuracyMeters":7.4},{"timestamp":"2026-04-25T10:01:00","latitude":37.769631,"longitude":-122.471172,"altitude":47,"speedMps":6.71,"courseDegrees":358,"horizontalAccuracyMeters":8.5}]}]}
